.gitignore
AUTHORS
LICENSE
README.md
setup.py
test/.gitignore
test/testBase.py
wallaby/FX.py
wallaby/__init__.py
wallaby/observer.py
wallaby/apps/__init__.py
wallaby/apps/baseApp.py
wallaby/common/__init__.py
wallaby/common/abstractService.py
wallaby/common/document.py
wallaby/common/draggable.py
wallaby/common/fxLogger.py
wallaby/common/lockable.py
wallaby/common/pathHelper.py
wallaby/common/queryDocument.py
wallaby/common/queryResult.py
wallaby/common/sets.py
wallaby/pf/__init__.py
wallaby/pf/configInterface.py
wallaby/pf/pillow.py
wallaby/pf/room.py
wallaby/pf/log/__init__.py
wallaby/pf/log/sdeditChannelFactory.py
wallaby/pf/peer/__init__.py
wallaby/pf/peer/abstractQuery.py
wallaby/pf/peer/actionButtonPeer.py
wallaby/pf/peer/booleanEditor.py
wallaby/pf/peer/booleanViewer.py
wallaby/pf/peer/configParty.py
wallaby/pf/peer/configuration.py
wallaby/pf/peer/credentials.py
wallaby/pf/peer/credentialsConsumer.py
wallaby/pf/peer/credentialsParty.py
wallaby/pf/peer/credentialsRouting.py
wallaby/pf/peer/database.py
wallaby/pf/peer/dateEditor.py
wallaby/pf/peer/dateViewer.py
wallaby/pf/peer/debugger.py
wallaby/pf/peer/dialog.py
wallaby/pf/peer/directEditDocument.py
wallaby/pf/peer/documentCache.py
wallaby/pf/peer/documentChanger.py
wallaby/pf/peer/documentCredentials.py
wallaby/pf/peer/documentCredentialsDatabase.py
wallaby/pf/peer/documentCredentialsDocument.py
wallaby/pf/peer/documentDatabase.py
wallaby/pf/peer/documentIDQueryResult.py
wallaby/pf/peer/documentPathEnabler.py
wallaby/pf/peer/documentViewer.py
wallaby/pf/peer/doubleEditor.py
wallaby/pf/peer/doubleViewer.py
wallaby/pf/peer/editDocument.py
wallaby/pf/peer/editDocumentDialog.py
wallaby/pf/peer/editParty.py
wallaby/pf/peer/editor.py
wallaby/pf/peer/embeddedViewer.py
wallaby/pf/peer/enableDocument.py
wallaby/pf/peer/enabler.py
wallaby/pf/peer/history.py
wallaby/pf/peer/idQueryResultDocument.py
wallaby/pf/peer/imageEditor.py
wallaby/pf/peer/imageViewer.py
wallaby/pf/peer/incrementalMultiViewer.py
wallaby_base.egg-info/PKG-INFO
wallaby_base.egg-info/SOURCES.txt
wallaby_base.egg-info/dependency_links.txt
wallaby_base.egg-info/requires.txt
wallaby_base.egg-info/top_level.txt